scanimage_webui/VERSION
scanimage_webui/__init__.py
scanimage_webui/app.py
scanimage_webui/main.py
scanimage_webui/libs/__init__.py
scanimage_webui/libs/scanner.py
scanimage_webui/libs/setuptools.py
scanimage_webui/libs/threads.py
scanimage_webui/static/css/app.css
scanimage_webui/static/css/croppr.css
scanimage_webui/static/img/crop-icon.png
scanimage_webui/static/img/delete-icon.png
scanimage_webui/static/img/reload-icon.png
scanimage_webui/static/img/rotate-l-icon.png
scanimage_webui/static/img/rotate-r-icon.png
scanimage_webui/static/img/scan-icon.png
scanimage_webui/static/js/app.js
scanimage_webui/static/js/croppr.js
scanimage_webui/static/js/jquery-3.3.1.min.js
scanimage_webui/static/js/utils.js
scanimage_webui/templates/index.html
scanimage_webui-1.2.6.dist-info/METADATA
scanimage_webui-1.2.6.dist-info/WHEEL
scanimage_webui-1.2.6.dist-info/entry_points.txt
scanimage_webui-1.2.6.dist-info/top_level.txt
scanimage_webui-1.2.6.dist-info/RECORD
