Metadata-Version: 2.1
Name: scanimage-webui
Version: 1.2.6
Summary: WEB UI for SANE scanimage command.
Home-page: https://gitlab.com/alda78/scanimage-webui
Author: Ales Adamek
Author-email: alda78@seznam.cz
License: MIT
Platform: UNKNOWN
Classifier: Programming Language :: Python :: 3
Classifier: License :: OSI Approved :: MIT License
Classifier: Operating System :: OS Independent
Requires-Python: >=3.6
Requires-Dist: flask
Requires-Dist: Pillow (==7.2)
